{"id":"110369","name":"Siya Infotech Solution Pvt. Ltd.","tagline":"Custom Software, POS & Web Application Development","profile":"/profile/siya-infotech-solution","website":"http://www.siyainfo.com","directory":"directory/mobile-application-developers","page":"245","verified":"","description":"We are one of the leading IT Companies in India, Working since 2009 for custom software, web and mobile application development. We are having splendid expertise with web apps development & POS development. We have developed Rapid RMS( www.rapidrms.com), a POS system which is ranked #1 in India & in top 10 in the world. \nPlease browse through our website www.siyainfo.com so that you may have a brief idea about our expertise and work experience. \nMoreover, we have more than 50 employees working in-house on various technologies with having great expertise. We are working on Asp. Net/ MVC/ C#, Native IOS & Android based mobile applications, PHP Development including Wordpress/ Magento/ Laravel/ CI, Database & Cloud application development, Web & Graphic designing, Quality Assurance & Analytic team along with highly experienced project managers for each technology we are working on. \nWe are working on agile software development process so that we can deliver project on time as well as with the highest client satisfaction rate. We are still growing & hiring to enlarge our team to work on some other in demand technologies like IoT, Machine Learning etc... \nIndustries we have worked with:\nINFORMATION TECHNOLOGY\nHOSPITAL & PHARMACEUTICAL\nHOTEL & RESERVATION\nEDUCATION INDUSTRY\nFINANCE INDUSTRY\nRETAIL MGMT INDUSTRY\nREAL ESTATE INDUSTRY\n \nREAD MORE...","min_project_size":"$1,000+","avg_hourly_rate":"$25 - $49 / hr","num_employees":"10 - 49","founded":"2009","locations":[{"headquarters":true,"address":"208 2nd floor, Sundaram Arcade, Science City Road","locality":"Ahmedabad","region":"GJ","postal_code":"380060","country":"India","phone":"+91 (079) 65534555"},{"headquarters":false,"address":"1100 Market St, Suite #903","locality":"Chattanooga","region":"TN","postal_code":"37402","country":"United States","phone":"888-727-4302"}]}