{"id":"153073","name":"Setelia","tagline":"The Expert In Mobile & IT","profile":"/profile/setelia","website":"http://www.setelia.com","directory":"directory/mobile-application-developers","page":"137","verified":"","description":"Setelia gives you access to its competences and the services of its expert teams in order to provide you with specialized solutions. We offer you a  certification process,  technological consulting, outsourcing, and mobile technologies so as to support your successful development.","min_project_size":"Undisclosed","avg_hourly_rate":"Undisclosed","num_employees":"50 - 249","founded":"2005","locations":[{"headquarters":true,"address":"2 rue Volney","locality":"Paris","region":"A75","postal_code":"75002","country":"France","phone":"+33 (0)1 55 43 26 00"},{"headquarters":false,"address":"Antablian Bldg 2703","locality":"Damascus Road, Baabda","region":"","postal_code":"","country":"Lebanon","phone":"+961 05 955 280"},{"headquarters":false,"address":"SilverSquare Avenue Louise, 523","locality":"Bruxelles","region":"BRU","postal_code":"1050","country":"Belgium","phone":"+32 470 203 801"}]}