{"id":"161518","name":"My Receptionist","tagline":"Virtual Receptionists","profile":"/profile/my-receptionist","website":"http://myreceptionist.com","directory":"bpo","page":"9","verified":"","description":"My Receptionist is a leading provider of on‐demand front office support for small businesses, providing the tools and personnel to ensure your business is always responsive.\nMy Receptionist streamlines your front office operations by leveraging its experienced staff to respond to client requests and free up your precious time.\nBasic info:\nNo free trial\nStarter: 70 mins for $100/mo\nCruising: 150 mins for $175/mo\nExpress: 235 mins for $250/mo","min_project_size":"Undisclosed","avg_hourly_rate":"Undisclosed","num_employees":"50 - 249","founded":"1996","locations":[{"headquarters":true,"address":"800 Wisconsin St. Suite 410","locality":"Eau Claire","region":"WI","postal_code":"54703","country":"United States","phone":"+1.800.686.0162"},{"headquarters":false,"address":"1505 20th Street","locality":"Vero Beach","region":"FL","postal_code":"32960","country":"United States","phone":""},{"headquarters":false,"address":"","locality":"Bengaluru","region":"","postal_code":"","country":"India","phone":""}]}