{"id":"176602","name":"Kosmos Central","tagline":"Integration Software","profile":"/profile/kosmos-central","website":"http://www.kosmoscentral.com","directory":"web-designers","page":"340","verified":"","description":"Kosmos Central is a leader in integration software. In the last 15 years we’ve worked with 100s of retail businesses to improve sales and simplify inventory management. By connecting point of sale, ERP and ecommerce applications we help retailers sell in more places and reduce data entry costs, allowing you to manage sales, inventory and customer data from multiple online and brick-and-mortar stores using your existing point of sale or ERP system.","min_project_size":"$10,000+","avg_hourly_rate":"$100 - $149 / hr","num_employees":"2 - 9","founded":"2001","locations":[{"headquarters":true,"address":"715 NW Hoyt Street, #6063","locality":"Portland","region":"OR","postal_code":"97228","country":"United States","phone":"888.256.7667"}]}