{"id":"198621","name":"Ascender Studios","tagline":"Designers, developers, thinkers & tinkerers","profile":"/profile/ascender-studios","website":"http://www.ascenderstudios.com","directory":"web-developers","page":"65","verified":"","description":"We are Ascender Studios. We are an independent studio of designers, developers, thinkers & tinkerers who take pride in everything we do.\nAt Ascender, we focus on building partnership-driven relationships while fast tracking your smart ideas to make them a reality.\nNo matter the vertical - healthcare, education, non-profit, retail or real estate - we hold the skills, which are ever evolving, to turn your ideas into engaging experiences. Our background imparts understanding across the broad business world - from the intricacies of helping start-ups seed to the tape of highly matrixed organizations. Take a look at our capabilities and see how we can help.\nREAD MORE...","min_project_size":"Undisclosed","avg_hourly_rate":"$100 - $149 / hr","num_employees":"2 - 9","founded":"2017","locations":[{"headquarters":true,"address":"","locality":"New York","region":"NY","postal_code":"","country":"United States","phone":""}]}