{"id":"202293","name":"AltSource, Inc","tagline":"Your Business. Your Way.","profile":"/profile/altsource","website":"https://www.altsourcesoftware.com","directory":"web-developers","page":"205","verified":"","description":"AltSource was founded in 2004 by Dave Moore and has a rich foundation of openness, diversity, and strong passion for what we do. We care about the wellbeing and success of every employee, customer, and product we build. Our culture and core values feature a compass guided by accountability, innovation, and integrity, and we pride ourselves on making a positive impact on every person and community we serve.\nWe at AltSource are change agents, strategists, engineers, innovators, and thought leaders. We live in a world of ideation, iteration, and disruption. Our Mission is simple: to deliver the highest-value custom applications to our clients. We ensure seamless integration of emerging technologies and delivery of exceptional future ready custom software solutions, featuring a focus on user experience, mobility, data management, and analytics.\nAltSource has been named to the Inc. 5000 List of Fastest Growing Private Companies in the U.S. every year since 2014 and has curated a hand-selected team of more than 150 in-house technical experts.\nREAD MORE...","min_project_size":"$250,000+","avg_hourly_rate":"$200 - $300 / hr","num_employees":"50 - 249","founded":"2004","locations":[{"headquarters":true,"address":"1120 SE Madison St.","locality":"Portland","region":"OR","postal_code":"97214","country":"United States","phone":"503.235.3316"}]}