{"id":"206100","name":"The Hucksters","tagline":"A Creative Boutique Ad Agency.","profile":"/profile/hucksters","website":"http://thehucksters.com","directory":"web-designers","page":"1219","verified":"","description":"The Hucksters is a streamlined, creative advertising agency that operates without the bureaucracy, trappings or expense of traditional agencies. We took our name from Frederic Wakeman's 1947 pulp novel The Hucksters, the story of an adman with ideals who registers a lone voice of dissent among a chorus of agency yes-men.\nBut we've adopted more than the name. We've adopted the spirit of the age. We believe in civility, not as some charming period piece, but as the cornerstone of all our relationships. But mostly, we're called The Hucksters because we're here to sell. And that's what we do.\nREAD MORE...","min_project_size":"$10,000+","avg_hourly_rate":"$150 - $199 / hr","num_employees":"2 - 9","founded":"Undisclosed","locations":[{"headquarters":true,"address":"8033 Sunset Boulevard. Ste., 1044,","locality":"Los Angeles","region":"CA","postal_code":"90046","country":"United States","phone":"713.222.2200"}]}