{"id":"214754","name":"MediaBros","tagline":"DIGITAL MARKETING AGENCY","profile":"/profile/mediabros","website":"https://mediabrosonline.com","directory":"seo-firms","page":"196","verified":"","description":"Bs As Consulting Solutions S.A. is a digital marketing agency, specialized in the development of advertising campaigns on the Internet. Our work is based on interpreting the needs of our clients, identifying the appropriate advertising opportunities for the companies and developing effective online marketing campaigns that reach the proposed objectives. Our executives are in continuous study and professional development for the correct analysis and measurement of yields of each campaign.","min_project_size":"$5,000+","avg_hourly_rate":"$25 - $49 / hr","num_employees":"2 - 9","founded":"2008","locations":[{"headquarters":true,"address":"Tte. General Juan Domingo Perón 315","locality":"Buenos Aires","region":"C","postal_code":"C1038AAG","country":"Argentina","phone":"+ 54 11.5258.2020"}]}