{"id":"22566","name":"Juego Studio","tagline":"A leading game development company","profile":"/profile/juego-studio-0","website":"https://www.juegostudio.com","directory":"directory/mobile-application-developers","page":"111","verified":"","description":"Started in 2011, Juego Studios has expanded from being a game design company to a full-fledged technology venture dealing with AR/VR, IoT, AI and other emerging technologies.We believe that constant innovation is the key to building successful products.\nAs a leading game development studio, we’re passionate and enthusiastic about experimenting with latest emerging technologies and strive to integrate creative vision, technical expertise and project management capabilities to ensure customer satisfaction.\nREAD MORE...","min_project_size":"$5,000+","avg_hourly_rate":"< $25 / hr","num_employees":"50 - 249","founded":"2011","locations":[{"headquarters":true,"address":"","locality":"","region":"","postal_code":"","country":"United States","phone":""}]}