{"id":"240495","name":"Depixion Studios","tagline":"We offer custom website solutions...","profile":"/profile/depixion-studios","website":"http://depixion.com","directory":"web-developers","page":"159","verified":"","description":"Web design, web development and search engine optimization for small and medium-sized businesses. We specialize in database-driven websites and internet applications for dynamic content, membership management, e-commerce and more.","min_project_size":"$5,000+","avg_hourly_rate":"$50 - $99 / hr","num_employees":"2 - 9","founded":"1990","locations":[{"headquarters":true,"address":"1100 Cherokee St Unit 304,","locality":"Denver","region":"CO","postal_code":"80204","country":"United States","phone":"303.670.7822"}]}