{"id":"25237","name":"TechDoodles","tagline":"Mobile apps, Games and web development company","profile":"/profile/techdoodles","website":"http://www.techdoodles.com","directory":"directory/mobile-application-developers","page":"45","verified":"","description":"TechDoodles is a software development firm having a small but talented mobile app, games and web engineers who are certainly capable of converting your idea into life.\nTop 5% in best React Native and iOS app developer on Upwork. TechDoodles is a synonym of trust, reliability and commitment when it comes to the mobile app, mobile games and websites development. Have a look at feedback from our esteem clients given below.\nWe will be more than happy to hear back from you to help you to create unique product that serves you the best.\nREAD MORE...","min_project_size":"Undisclosed","avg_hourly_rate":"< $25 / hr","num_employees":"10 - 49","founded":"2014","locations":[{"headquarters":true,"address":"707, Westgate, SG Highway, Ahmedabad","locality":"Ahmedabad","region":"","postal_code":"380015","country":"India","phone":"91.903.300.8990"},{"headquarters":false,"address":"","locality":"","region":"","postal_code":"","country":"India","phone":""}]}