{"id":"25405","name":"Webespire Consulting","tagline":"Innovation Inspired by Technology","profile":"/profile/webespire-consulting","website":"http://www.webespire.com","directory":"directory/mobile-application-developers","page":"69","verified":"","description":"Webespire Consultancy is a trusted name well recognized for offering IT software technology services, offshore web design, IT software product development across the globe. We provide back to back business solutions to all our clients and always ready to help you in web designing, development and implementation of solutions as per your needs.\nWe are a globally recognized offshore website design agency and we have professional web designers, who work on your website design and complete your website, as per our committed time with affordable cost within your defined budget.\nbusiness technology consulting, IT software solutions, offshore web design india, web Development india, mobile apps development, IT software consulting, IT software product engineering\nYour business has unique needs. As a web development company, we are here to satisfy those needs. It is not just a creative web design. Our web developers will make sure your website is a sure way to online success.\nWe at Webespire Consulting provide Web-based ERP solutions, Android app development, Ios app development and Customized software solutions at affordable price.\nREAD MORE...","min_project_size":"Undisclosed","avg_hourly_rate":"< $25 / hr","num_employees":"10 - 49","founded":"2013","locations":[{"headquarters":true,"address":"C 22/14 Sector 57","locality":"Noida","region":"UP","postal_code":"201301","country":"India","phone":"+911204292626"}]}