{"id":"255447","name":"Good Monster","tagline":"Good People. Great Marketing.","profile":"/profile/good-monster","website":"http://thegoodmonster.com","directory":"web-designers","page":"679","verified":"","description":"Good Monster is a fast growing marketing agency based in Syracuse, NY, with a network of team members that span the globe. Our mission is to design brand building strategies while driving top line revenue for our clients. Our digital marketing agency works to drive business results with social media, SEO, web design & much more.","min_project_size":"$1,000+","avg_hourly_rate":"$100 - $149 / hr","num_employees":"2 - 9","founded":"2012","locations":[{"headquarters":true,"address":"327 West Fayette St. Ste 212","locality":"Syracuse","region":"NY","postal_code":"13202","country":"United States","phone":"315-226-3269"}]}