{"id":"261225","name":"Nimbus Marketing","tagline":"Easy Online Marketing","profile":"/profile/nimbus-marketing","website":"https://nimbusmarketinggroup.com","directory":"web-designers","page":"51","verified":"","description":"you need an online marketing strategy that works. But managing it all at once can be difficult for a business. You have so many other things to deal with in running your business than to immerse yourself in the world of online marketing Los Angeles. Maybe you’re looking for some search engine optimization consulting or help with marketing through social media. Which of the many search engine optimization sites will you turn to for the most successful online internet advertising campaigns?\n \nNimbus Marketing handles your keyword research, search engine optimization, social media marketing, and website design needs, so you can focus on running your business FIRST. We can also help with pay per click advertising, and through our extensive pay per click management services, we can help you design the best pay per click program for your business, so you can get your business getting more potential customers fast! Our online marketing services cover everything a business needs to get to that coveted first page of the results people’s use of search engine services.  Your website traffic will increase dramatically with our full range of SEO services\n \nSo what are you waiting for? For the best in search engine optimization and social media marketing.\nREAD MORE...","min_project_size":"$5,000+","avg_hourly_rate":"$100 - $149 / hr","num_employees":"2 - 9","founded":"2007","locations":[{"headquarters":true,"address":"925 N La Brea Ave Fl 4","locality":"Los Angeles","region":"CA","postal_code":"90038","country":"United States","phone":"310.486.1154"}]}