{"id":"262116","name":"Counterintuity","tagline":"Marketing + Strategy","profile":"/profile/counterintuity","website":"https://counterintuity.com","directory":"web-designers","page":"449","verified":"","description":"Counterintuity’s new marketing for now approach has helped hundreds of small and mid-sized businesses as well as non-profits and public agencies enhance their reach, boost sales, serve their customers, and improve their bottom line.\nOur multi-platform marketing campaigns include a full suite of online, offline and design capabilities unified toward your success.","min_project_size":"$5,000+","avg_hourly_rate":"$100 - $149 / hr","num_employees":"10 - 49","founded":"2007","locations":[{"headquarters":true,"address":"3305 W. Burbank Boulevard","locality":"Burbank","region":"CA","postal_code":"91505","country":"United States","phone":"+1.818.848.1700"}]}