{"id":"270270","name":"Rejoin Web Solution Pvt. Ltd.","tagline":"Stay ahead with our vision","profile":"/profile/rejoin-web-solution","website":"https://www.rejoinwebsolution.com","directory":"directory/mobile-application-developers","page":"310","verified":"","description":"Rejoin Web Solution is top notch web design and development company. Our company headquarters is located in Mohali, India. We are offering a complete range of CMS development services including Wordpress development, Shopify Development, and Magento Development Company. Our team is Equipped with the latest tools and technologies to deliver outstanding results to our esteemed clients.\nWhether it is website design, development of eCommerce Website or Mobile app development, We can cater excellent solutions for every client’s need. \nREAD MORE...","min_project_size":"$1,000+","avg_hourly_rate":"< $25 / hr","num_employees":"10 - 49","founded":"2011","locations":[{"headquarters":true,"address":"Phase 8-B, Industrial Area","locality":"Punjab","region":"","postal_code":"160055","country":"India","phone":"0172-4185253"}]}