{"id":"27686","name":"Startechup Inc.","tagline":"SOFTWARE DEVELOPMENT - WEB AGENCY - PHILIPPINES","profile":"/profile/startechup","website":"http://www.startechup.com","directory":"web-developers","page":"104","verified":"","description":"Startechup Inc. is a Web and Software Development Agency based in Cebu City, Philippines. Startechup specializes in providing IT, Web, and Mobile solutions for some of the most exciting startups and progressive enterprises globally. Startechup Inc. was incorporated in November 2013 for building up a team of talented IT engineers and designers to create the first online application connecting people and NGOs (\nwww.globedrop.org)\nREAD MORE...","min_project_size":"Undisclosed","avg_hourly_rate":"$25 - $49 / hr","num_employees":"10 - 49","founded":"2013","locations":[{"headquarters":true,"address":"","locality":"Cebu City","region":"","postal_code":"6000","country":"Philippines","phone":""}]}