{"id":"278709","name":"Junction Marketing Agency","tagline":"There's another way","profile":"/profile/junction-marketing-agency","website":"http://www.junction-agency.com","directory":"web-designers","page":"1012","verified":"","description":"That’s what we do with marketing. We are Junction, we are connected. We devise, sculpt and execute world-class marketing programmes. From our founders through the whole team, we care about harnessing the great and the good of marketing tools and techniques. Traditional, new and overlooked channels and platforms are our way to help businesses like yours Reach new prospects and markets.\nRaise your brand as well as Raise hands of potential customers and Elevate your pipeline, your stock (with customers and your colleagues) your levels of success and return from marketing spend and effort. We’ve been doing this as a collective for nearly sixty years and whether you sell direct, via partners, the channel or all of the above, we can help.\nREAD MORE...","min_project_size":"$10,000+","avg_hourly_rate":"$150 - $199 / hr","num_employees":"10 - 49","founded":"2014","locations":[{"headquarters":true,"address":"Challenge House Sherwood Drive","locality":"Milton Keynes","region":"","postal_code":"MK3 6DP","country":"United Kingdom","phone":"01908.533421"}]}