{"id":"37688","name":"Galaxy Weblinks","tagline":"Custom software development in Boston","profile":"/profile/galaxy-weblinks","website":"https://www.galaxyweblinks.com","directory":"web-developers","page":"3","verified":"","description":"Galaxy is a web development & mobile app development company established in 1998. With over 1000+ projects delivered to over 200+ clients, we provide technical expertise with 24/7 support.\nOur first and most important job: to help our clients understand the totality of the technology landscape and conceive, design, implement, and support solutions that fit their needs – and budgets. \nArea of expertise\nMobile apps- Android, iOS and Hybrid (phonegap)\nOpen Source Developement\nWeb development and design\nNetwork, support and maintenance\nREAD MORE...","min_project_size":"Undisclosed","avg_hourly_rate":"$25 - $49 / hr","num_employees":"50 - 249","founded":"1998","locations":[{"headquarters":true,"address":"745 atlantic ave","locality":"Boston","region":"MA","postal_code":"02111","country":"United States","phone":"888.666.4316"},{"headquarters":false,"address":"75 E W Santa Clara St","locality":"San Jose","region":"CA","postal_code":"95113","country":"United States","phone":"888.444.4316"},{"headquarters":false,"address":"2130 Millennium Dr","locality":"Los Angeles","region":"CA","postal_code":"90094","country":"United States","phone":"888.666.4316"},{"headquarters":false,"address":"78 SW 7th St","locality":"Miami","region":"FL","postal_code":"33130","country":"United States","phone":"888.666.4316"},{"headquarters":false,"address":"1920 McKinney Ave","locality":"Dallas","region":"TX","postal_code":"75201","country":"United States","phone":"888.666.4316"},{"headquarters":false,"address":"206 shalimar corporate center","locality":"Indore","region":"","postal_code":"452001","country":"India","phone":""},{"headquarters":false,"address":"","locality":"Madurai","region":"","postal_code":"625001","country":"India","phone":""}]}