{"id":"41567","name":"Webixion Technologies LLC","tagline":"Innovative Ideas, Great Designs","profile":"/profile/webixion-technologies","website":"http://www.webixion.com","directory":"directory/mobile-application-developers","page":"71","verified":"","description":"Webixion Technologies LLC provides cost effective web and mobile solutions worldwide for 11 years.\nOur Services - - Web & Mobile Re-Engineering services - Product Development & Maintenance - Writing SRS, Feasibility Study & Other Market Research Services - Native & Hybrid Mobile Applications - Test Cases development and dedicated QA services are why clients prefer Webixion Technologies - - Backed by 35+ dedicated high skilled software professionals - a State of the art development center with 24 hrs power backup and multiple internet leased lines - Excellent written and verbal English communication - Leading freelancer service provider in India - 24/7 support (multiple phone lines) - Milestone based development approach - Internal KANBAN based project management system - Agile methodology to accommodate changes and thoughts at any stage of development\nREAD MORE...","min_project_size":"$1,000+","avg_hourly_rate":"< $25 / hr","num_employees":"10 - 49","founded":"2008","locations":[{"headquarters":true,"address":"16192 Coastal Hwy","locality":"Lewes","region":"DE","postal_code":"19958","country":"United States","phone":"302 907-9856"},{"headquarters":false,"address":"39-11-5, 1st Floor, Murali Nagar","locality":"Visakhapatnam","region":"AP","postal_code":"530007","country":"India","phone":"7799888920"}]}