{"id":"47395","name":"JustCoded","tagline":"Technology Consulting and Web Development","profile":"/profile/justcoded","website":"https://justcoded.com","directory":"web-developers","page":"2","verified":"","description":"We create digital web solutions for tech startups and established businesses in Online investment, Crowdfunding, Real Estate, Luxury, Travel, and Art sectors.\nOur goal is to help you build the product from the ground up and overcome challenges with tech and business guidance, involvement, and support at every stage of the journey.\nWith the mission to transform the traditional financial industry and deep expertise in the crowdfunding niche, we build financial solutions to our clients from the UK and Europe: crowdfunding, P2P lending, and other investment platforms.\nWe listen, understand, co-create, and deliver.\nREAD MORE...","min_project_size":"$10,000+","avg_hourly_rate":"$50 - $99 / hr","num_employees":"50 - 249","founded":"2007","locations":[{"headquarters":true,"address":"2 Stephen St","locality":"London","region":"LND","postal_code":"W1T 1AN","country":"United Kingdom","phone":"02080128484"},{"headquarters":false,"address":"Lopans’kyi Ln, 10","locality":"Kharkiv","region":"","postal_code":"61052","country":"Ukraine","phone":"00442071933818"},{"headquarters":false,"address":"","locality":"","region":"","postal_code":"","country":"Ukraine","phone":""}]}