{"id":"59628","name":"PROBESEVEN","tagline":"Web, Brand & the Business.","profile":"/profile/probeseven","website":"http://www.probeseven.com","directory":"directory/mobile-application-developers","page":"198","verified":"","description":"PROBESEVEN, the leading provider of technology and IT solutions across different nations. Dedicated to help clients transform to the competitive edge with high productivity and better collaboration. \n\nOur services are an array of top-notch technology with deep expertise resulting from service provided to varied industries across the globe. Deliver wide range of branded and unique concept and get proficient over the most complex IT solutions. Profoundly dedicated are the team of varied talents creative and diversified coming together to serve the global clients with the fullest satisfaction.\nREAD MORE...","min_project_size":"Undisclosed","avg_hourly_rate":"Undisclosed","num_employees":"10 - 49","founded":"2006","locations":[{"headquarters":true,"address":"#88,89, SSN Square - Floor4, Near RTO Office, Peelamedu Pudur,","locality":"Coimbatore","region":"TN","postal_code":"641004","country":"India","phone":"+91 422 4382548"},{"headquarters":false,"address":"#55, Sakthi Towers - Floor3, Bharathi Street, Valipalayam,","locality":"Tiruppur","region":"TN","postal_code":"641601","country":"India","phone":"+91 421 4322548"},{"headquarters":false,"address":"#146, Green Sleeves, Hosur Main Road, Singasandra,","locality":"Bangalore","region":"KA","postal_code":"560068","country":"India","phone":"+91 7708797777"}]}