{"id":"64718","name":"Technovinity Systems Pvt Ltd","tagline":"Excellent Quality : Excellent Relationship","profile":"/profile/technovinity-systems","website":"http://www.technovinity.com","directory":"web-designers","page":"735","verified":"","description":"We can provide the service in website development,designing and seo. paypal integration etc .","min_project_size":"$1,000+","avg_hourly_rate":"< $25 / hr","num_employees":"10 - 49","founded":"2013","locations":[{"headquarters":true,"address":"","locality":"","region":"","postal_code":"","country":"India","phone":""}]}