{"id":"65574","name":"Agasti Technologies Private Limited","tagline":"Delivering Value Through Innovation","profile":"/profile/agasti-technologies-private","website":"http://www.agastitech.com","directory":"directory/mobile-application-developers","page":"391","verified":"","description":"Agasti Technologies is a one stop solution for technology/IT startups and entrepreneurs who have great ideas and want to turn them into a product. Agasti Tech was founded in May 2015. We are helping start-ups right from the prototyping of the idea to the launching of the product and digital marketing of the product.\nAgasti Technologies has a dedicated team of extremely talented, customer-focused and diligent individuals who have a diversified skill set. The teams at Agasti Technologies abide by stringent quality standards and tailor their processes to provide state-of-the-art services to their customers. Our transparent, efficient and flexible processes help us create software solutions that meet present and future demands.\nREAD MORE...","min_project_size":"$1,000+","avg_hourly_rate":"< $25 / hr","num_employees":"10 - 49","founded":"2015","locations":[{"headquarters":true,"address":"","locality":"Akole","region":"","postal_code":"","country":"India","phone":""}]}