{"id":"68569","name":"Zymr, Inc.","tagline":"Concept to Cloud. Perfected.","profile":"/profile/zymr","website":"http://www.zymr.com","directory":"directory/mobile-application-developers","page":"58","verified":"","description":"Zymr is a Silicon Valley-based full-stack cloud consulting and software development company, that integrates state-of-the-art software paradigms, agile development culture, and global delivery centers. Since 2012, Zymr’s clients have enjoyed access to premium engineering services to support disruptive business models and challenging development time lines.\n \nZymr works with some of the most demanding venture-funded startups and mid-to-large enterprises, to render their cloud-enabled products and services. This has helped Zymr’s customers quickly evolve and create pathbreaking innovations to outperform competitors by leveraging Zymr’s domain knowledge and full-stack expertise to build scalable and secure cloud products.\n \nZymr has generated significant returns and strategic business value for its customers through its deep expertise in relevant cloud, mobile and open source technologies, and its strong focus on the needs of product and solution end-users. With a proven track record, mature engineering and design teams, a fast growing roster of delighted clients, and veteran management, Zymr is a solutions partner of choice.\nREAD MORE...","min_project_size":"$25,000+","avg_hourly_rate":"$25 - $49 / hr","num_employees":"50 - 249","founded":"2012","locations":[{"headquarters":true,"address":"1798 Technology Drive, Suite-229","locality":"San Jose","region":"CA","postal_code":"95110","country":"United States","phone":"408.463.6610"}]}