{"id":"77734","name":"My Biz Niche","tagline":"We rescue failed online marketing campaigns","profile":"/profile/my-biz-niche","website":"https://www.mybizniche.com","directory":"web-designers","page":"66","verified":"","description":"My Biz Niche rescues failed online marketing projects.\nStruggling to get business online? It’s probably because your website doesn’t have the right messaging, loads slow, old coding or is not secure. Websites also need to be properly structured to rank for targeted keywords in search engines and to obtain a higher ROI through paid online advertising.\nYou need the correct resources to get the job done. Our team consists of highly talented individuals who specialize in their field of online marketing. Our team consists of talented web designers, developers, account managers, writers, SEO strategists and PPC experts.\nREAD MORE...","min_project_size":"$1,000+","avg_hourly_rate":"$100 - $149 / hr","num_employees":"10 - 49","founded":"2014","locations":[{"headquarters":true,"address":"","locality":"scottsdale","region":"AZ","postal_code":"","country":"United States","phone":""}]}