{"id":"94604","name":"Mobillers","tagline":"Innovation and tech solutions.","profile":"/profile/mobillers","website":"http://www.mobillers.com","directory":"directory/mobile-application-developers","page":"174","verified":"","description":"We are a developer company of Software, Apps and Technology Integration. We are made up of professionals with extensive experience in the technological sector and we have our own products and a team of developers at your disposal to make custom work.","min_project_size":"$5,000+","avg_hourly_rate":"$25 - $49 / hr","num_employees":"2 - 9","founded":"2014","locations":[{"headquarters":true,"address":"Baez 345 1° 3°, Ciudad","locality":"Buenos Aires","region":"","postal_code":"","country":"Argentina","phone":"0810-345-3399"}]}