{
  "urls": {
    "http://www.kconsultinggroup.com/": {
      "status": 200
    },
    "https://www.kconsultinggroup.com/": {
      "status": 200
    },
    "https://www.kconsultinggroup.com/design/": {
      "status": 200
    },
    "https://www.kconsultinggroup.com/logo-development/": {
      "status": 200
    },
    "https://www.kconsultinggroup.com/brochure-creation/": {
      "status": 200
    },
    "https://www.kconsultinggroup.com/advertising-and-billboards/": {
      "status": 200
    },
    "https://www.kconsultinggroup.com/postcards/": {
      "status": 200
    },
    "https://www.kconsultinggroup.com/banners-and-posters/": {
      "status": 200
    },
    "https://www.kconsultinggroup.com/website-development/": {
      "status": 200
    },
    "https://www.kconsultinggroup.com/legal-websites/": {
      "status": 200
    },
    "https://www.kconsultinggroup.com/starter-business-packages/": {
      "status": 200
    }
  },
  "applications": [
    {
      "name": "Apache",
      "confidence": "100",
      "version": null,
      "icon": "Apache.svg",
      "website": "http://apache.org",
      "cpe": "cpe:/a:apache:http_server",
      "categories": [
        {
          "22": "Web Servers"
        }
      ]
    },
    {
      "name": "Font Awesome",
      "confidence": "100",
      "version": null,
      "icon": "Font Awesome.png",
      "website": "http://fontawesome.io",
      "cpe": null,
      "categories": [
        {
          "17": "Font Scripts"
        }
      ]
    },
    {
      "name": "Google Analytics",
      "confidence": "100",
      "version": null,
      "icon": "Google Analytics.svg",
      "website": "http://google.com/analytics",
      "cpe": null,
      "categories": [
        {
          "10": "Analytics"
        }
      ]
    },
    {
      "name": "Google Font API",
      "confidence": "100",
      "version": null,
      "icon": "Google Font API.png",
      "website": "http://google.com/fonts",
      "cpe": null,
      "categories": [
        {
          "17": "Font Scripts"
        }
      ]
    },
    {
      "name": "Lightbox",
      "confidence": "100",
      "version": null,
      "icon": "Lightbox.png",
      "website": "http://lokeshdhakar.com/projects/lightbox2/",
      "cpe": "cpe:/a:lightbox_photo_gallery_project:lightbox_photo_gallery",
      "categories": [
        {
          "59": "JavaScript Libraries"
        }
      ]
    },
    {
      "name": "PHP",
      "confidence": "100",
      "version": null,
      "icon": "PHP.svg",
      "website": "http://php.net",
      "cpe": "cpe:/a:php:php",
      "categories": [
        {
          "27": "Programming Languages"
        }
      ]
    },
    {
      "name": "Revslider",
      "confidence": "100",
      "version": "5.4.8",
      "icon": "revslider.png",
      "website": "https://revolution.themepunch.com/",
      "cpe": null,
      "categories": [
        {
          "19": "Miscellaneous"
        }
      ]
    },
    {
      "name": "Slick",
      "confidence": "100",
      "version": null,
      "icon": "default.svg",
      "website": "https://kenwheeler.github.io/slick",
      "cpe": null,
      "categories": [
        {
          "59": "JavaScript Libraries"
        }
      ]
    },
    {
      "name": "WordPress",
      "confidence": "100",
      "version": "4.8.2",
      "icon": "WordPress.svg",
      "website": "https://wordpress.org",
      "cpe": null,
      "categories": [
        {
          "1": "CMS"
        },
        {
          "11": "Blogs"
        }
      ]
    },
    {
      "name": "Yoast SEO",
      "confidence": "100",
      "version": "4.3",
      "icon": "Yoast SEO.png",
      "website": "http://yoast.com",
      "cpe": null,
      "categories": [
        {
          "54": "SEO"
        }
      ]
    },
    {
      "name": "YouTube",
      "confidence": "100",
      "version": null,
      "icon": "YouTube.png",
      "website": "http://www.youtube.com",
      "cpe": null,
      "categories": [
        {
          "14": "Video Players"
        }
      ]
    },
    {
      "name": "animate.css",
      "confidence": "100",
      "version": null,
      "icon": "default.svg",
      "website": "https://daneden.github.io/animate.css/",
      "cpe": null,
      "categories": [
        {
          "66": "UI Frameworks"
        }
      ]
    },
    {
      "name": "jQuery",
      "confidence": "100",
      "version": "1.12.4",
      "icon": "jQuery.svg",
      "website": "https://jquery.com",
      "cpe": null,
      "categories": [
        {
          "59": "JavaScript Libraries"
        }
      ]
    },
    {
      "name": "jQuery Migrate",
      "confidence": "100",
      "version": "1.4.1",
      "icon": "jQuery.svg",
      "website": "https://github.com/jquery/jquery-migrate",
      "cpe": null,
      "categories": [
        {
          "59": "JavaScript Libraries"
        }
      ]
    },
    {
      "name": "jQuery Mobile",
      "confidence": "100",
      "version": "5.0.37",
      "icon": "jQuery Mobile.svg",
      "website": "https://jquerymobile.com",
      "cpe": null,
      "categories": [
        {
          "26": "Mobile Frameworks"
        }
      ]
    },
    {
      "name": "MySQL",
      "confidence": "0",
      "version": null,
      "icon": "MySQL.svg",
      "website": "http://mysql.com",
      "cpe": "cpe:/a:mysql:mysql",
      "categories": [
        {
          "34": "Databases"
        }
      ]
    }
  ],
  "meta": {
    "language": "en-US"
  },
  "website": "http://www.kconsultinggroup.com",
  "id": "20962"
}